ltime/__init__.py
ltime/__version__.py
ltime/ltime.py
ltime/util.py
ltime-0.0.5.dist-info/METADATA
ltime-0.0.5.dist-info/RECORD
ltime-0.0.5.dist-info/WHEEL
ltime-0.0.5.dist-info/top_level.txt
