Metadata-Version: 2.1
Name: ltime
Version: 0.0.5
Summary: My short description for my project.
Home-page: https://github.com/fanjindong/ltime
Author: fanjindong
Author-email: 765912710@qq.com
License: MIT
Platform: UNKNOWN
Classifier: License :: OSI Approved :: MIT License
Classifier: Programming Language :: Python
Classifier: Programming Language :: Python :: 3
Classifier: Programming Language :: Python :: 3.6
Classifier: Programming Language :: Python :: Implementation :: CPython
Classifier: Programming Language :: Python :: Implementation :: PyPy
Requires-Python: >=3.5.0
